<InterfaceSummary>
<RtlPorts>
<name>id_filter_V</name>
<CType>
<TypeName>ap_uint 3</TypeName>
<TypeWidth>3</TypeWidth>
<PhysicalWidth>3</PhysicalWidth>
</CType>
<CFractionWidth>0</CFractionWidth>
<InvalidType>0</InvalidType>
</RtlPorts>
<RtlPorts>
<name>in_img_V</name>
<CType>
<TypeName>ap_uint 8</TypeName>
<TypeWidth>8</TypeWidth>
<PhysicalWidth>8</PhysicalWidth>
</CType>
<CFractionWidth>0</CFractionWidth>
<InvalidType>0</InvalidType>
</RtlPorts>
<RtlPorts>
<name>out_img_V</name>
<CType>
<TypeName>ap_uint 8</TypeName>
<TypeWidth>8</TypeWidth>
<PhysicalWidth>8</PhysicalWidth>
</CType>
<CFractionWidth>0</CFractionWidth>
<InvalidType>0</InvalidType>
</RtlPorts>
</InterfaceSummary>

